CHANGES.rst
MANIFEST.in
readme.rst
run_tests.py
setup.py
macropy/__init__.py
macropy/activate.py
macropy/case_classes.py
macropy/console.py
macropy/peg.py
macropy/quick_lambda.py
macropy/string_interp.py
macropy/tracing.py
macropy/core/__init__.py
macropy/core/analysis.py
macropy/core/cleanup.py
macropy/core/compat.py
macropy/core/console.py
macropy/core/exact_src.py
macropy/core/exporters.py
macropy/core/failure.py
macropy/core/gen_sym.py
macropy/core/hquotes.py
macropy/core/import_hooks.py
macropy/core/macros.py
macropy/core/quotes.py
macropy/core/util.py
macropy/core/walkers.py
macropy/experimental/__init__.py
macropy/experimental/js_snippets.py
macropy/experimental/pattern.py
macropy/experimental/pinq.py
macropy/experimental/pyxl_strings.py
macropy/experimental/tco.py
macropy3.egg-info/PKG-INFO
macropy3.egg-info/SOURCES.txt
macropy3.egg-info/dependency_links.txt
macropy3.egg-info/requires.txt
macropy3.egg-info/top_level.txt