Metadata-Version: 1.1
Name: macropy3
Version: 1.0.4.dev2
Summary: Macros for Python: Quasiquotes, Case Classes, LINQ and more!
Home-page: https://github.com/azazel75/macropy
Author: Alberto Berti
Author-email: alberto@metapensiero.it
License: MIT
Platform: UNKNOWN
Classifier: Programming Language :: Python :: 3.5
Classifier: Programming Language :: Python :: 3.6
